extzip/__init__.py
extzip/__main__.py
extzip/extzip.py
extzip-0.2.dist-info/METADATA
extzip-0.2.dist-info/WHEEL
extzip-0.2.dist-info/top_level.txt
extzip-0.2.dist-info/RECORD
