Metadata-Version: 2.1
Name: extzip
Version: 0.2
Summary: zip extfile in path
Home-page: https://gitee.com/wdy0401/zipdir
Author: wangdeyang
Author-email: wdy0401@gmail.com
License: MIT
Requires-Dist: syutils >=0.0.5
